pyhyperpath.so
pydhs/__init__.py
pydhs/hello.py
pydhs/sample/__init__.py
pydhs/sample/__init__.pyc
pydhs-1.5.3.dist-info/DESCRIPTION.rst
pydhs-1.5.3.dist-info/METADATA
pydhs-1.5.3.dist-info/RECORD
pydhs-1.5.3.dist-info/WHEEL
pydhs-1.5.3.dist-info/metadata.json
pydhs-1.5.3.dist-info/top_level.txt
