Metadata-Version: 2.0
Name: pydhs
Version: 1.5.3
Summary: Python wrapper of C++ Hyperpath algorithm implementation, requires python-dev, boost_python installed
Home-page: http://fukudalab.hypernav.mobi
Author: Jiangshan(Tonny) Ma
Author-email: tonny.achilles@gmail.com
License: MIT
Keywords: hyperpath
Platform: UNKNOWN
Classifier: Development Status :: 3 - Alpha
Classifier: Intended Audience :: Developers
Classifier: Topic :: Software Development :: Build Tools
Classifier: License :: OSI Approved :: MIT License
Classifier: Programming Language :: Python :: 2.7
